toc4github.py
toc4github-0.17.dist-info/METADATA
toc4github-0.17.dist-info/WHEEL
toc4github-0.17.dist-info/licenses/LICENSE
toc4github-0.17.dist-info/RECORD
