Metadata-Version: 2.1
Name: toc4github
Version: 0.17
Summary: To automatically generate Table of Contents (TOC) for markdown file, especially for README.md of Github.com
Project-URL: homepage, https://github.com/xinlin-z/toc4github
Author-email: xinlin-z <xinlin.zhang@hotmail.com>
License: MIT License
License-File: LICENSE
Keywords: README.md,TOC,github,markdown
Classifier: License :: OSI Approved :: MIT License
Classifier: Operating System :: OS Independent
Classifier: Programming Language :: Python :: 3
Requires-Python: >=3.8
